{
  "id": 678431,
  "kind": "guide",
  "title": "伊瑟PVP之RTA阵容推荐和搭配",
  "domainPath": [
    "03_攻略参考",
    "04_PVP攻略"
  ],
  "classifyReason": "PVP攻略、榜单或评测参考",
  "originalCategory": "07_攻略评测",
  "text": "伊瑟PVP之RTA阵容推荐和搭配\n\n嗨喽，各位超链者，韶华结合自己的理解给大家伙浅聊一下。随着开服至今新卡的不断推出让各种流派和阵容逐渐完善，现在已经不是S0赛季以速度为主要最求的策略了。更多看重的是你对于自己账号发展的规划和养成方向，以及RTA比赛目前最为重要的BAN/PICK环节（以下简称“BP”），很多时候大家比拼的是对于自己养\n\n嗨喽，各位超链者，韶华结合自己的理解给大家伙浅聊一下。\n\n随着开服至今新卡的不断推出让各种流派和阵容逐渐完善，现在已经不是S0赛季以速度为主要最求的策略了。\n\n更多看重的是你对于自己**账号发展的规划和养成方向**，以及RTA比赛目前最为重要的**BAN/PICK环节（以下简称“BP”）**，很多时候大家比拼的是对于自己养成阵容**上阵的搭配思路和对对方阵容的拆解**，目的就是瓦解对面的阵容，进行针对和属性克制，将己方优势最大化，还有对局内**局势的快速分析**，见招拆招来赢得比赛。\n\n不仅要靠练度，还要靠思路。\n\nS1赛季我总计打了**57**局（含赛季初定级赛失误3局），**80%+**的胜率，顺利拿到低保。\n\n不然的话胜率还可以再高一点。\n\n由于存在相性的**互相克制**的机制存在，那么当对方的关键位置（举例：对面拿出来异属性龙妈，那么我们可以拿出虚属性罗睺打一手克制。光暗同理）\n\n这样可以在阵容上阵搭配的同时起到克制对面的作用。\n\n当然，这也不是绝对的。当你的阵容搭建，功能互补等机制利用效率很高的话，也不是不能**逆属性**取胜。\n\n正常情况下先手速攻核爆被肉队克制，肉队被中高速速度控制队克制，反过来速控队被速攻核爆克制。\n\n反之受不同玩家账号练度情况不同，配速不同，源器+智壳搭配效果的不同，临场BP&对战打法等的种种不同因素的影响下。上面的说法也不绝对，**没有绝对的稳赢的阵容队伍存在****。**\n\n**来吧 ！ 展示 ！！**\n\n**（因玩家不同的思路&想法&打法等不同，不会过多推荐源器和智壳的搭配哈）**\n\n**以下为先手速攻核爆&中高速控制（纯控制/+输出）阵容推荐**\n\n玩先手速攻核爆阵容，你要对自己的速度装备和智壳重构**自信**才行，讲究的就是**力大飞砖**的效果，即快速高效的完成一场对局。\n\n该类阵容推荐3号保护位选择主C，也可以选择双C（更为暴力）。\n\n推拉条的位置，纯核爆建议选择**双**推拉条，因为会被大概率ban掉一个。（比如芙蕾雅的被动“梦引”的推拉条，抢速一把手。）\n\n功能辅助位的存在是为了己方的输出最大化，比如逆翎的驱散&破防&虚弱&降速和专属buff“逆羽”可以最大化输出的同时，提高己方的生存。）\n\n也可以在速攻核爆的阵容内，上阵控制类角色（控制对面多个回合，极大的提高我方的容错）\n\n也可以纯控制，我的回合~我的回合~~还是我的回合~~~，尽情的燃烧脑细胞，享受**精准计算**的感觉。\n\n**以下为后手沉底肉队&中高速肉队&肉控阵容推荐**\n\n肉队的核心源器就是**“浴血”**，他才是肉队的灵魂和完全体。智壳的要求也是**优先选择带有浴血**（某些特定搭配的卡，需要硬凑12浴血除外。）\n\n沉底肉队讲究的就是肉度和血量，在浴血的加持下，讲究的就是抗打，对面核不掉我，那么就开始我的表演了。\n\n中高速肉队，就是沉底肉队的**进阶版**了，需要更高的整体练度了，再碰到同样是肉队的内战中往往占据速度优势，意味着更多的出手机会和更快的技能CD轮转。\n\n同样的，在中高速肉队的前提下，加入上图核爆阵容推荐里面的“控制”功能的卡（同样带的也是“浴血”的源器和智壳）提高容错。\n\n**以下为反制快攻核爆&速控对策卡推荐**\n\n**赫妍**：推荐带有“戍卫”的“伯爵”智壳，有效防控的同时+1200攻击力可以更好的保证击杀复活队友和吸血续航。\n\n**维罗妮卡**：推荐带有“戍卫”的“双速”智壳，一技能被动点到等级4的前提下，受到攻击可以提升行动条35%，来释放大招（最重要的是释放群体**“灵魂守护”**，和偷取对面关键增益效果**扩散**至全体成员。）\n\n**彼岸汀：**推荐带“琥珀”智壳，最重要的二技能优先点至等级4，可以更好的拉起己方C位和减技能冷却CD来释放反击一击。\n\n**莉拉姆：**目前唯一被动**“一闪”**（免疫所有控制效果--一技能点满将额外免疫击退行动条的效果）控制队的克星。\n\n**凌罗：**推荐带“死神脚步”智壳，选择疾驰+奋进+迅光智壳，右三都带效果抵抗，副属性优先选择速度和效果抵抗。但凡抵抗一次，就可以实现完美超车，释放大招，全体队友覆盖免疫效果。\n\n**宁芙涅：**阵容搭配同凌罗。（现阶段优选肯定是“死神脚步”这个智壳，因为主属性效果抵抗高速的源器不是那么容易做出来的。随着练度的不断提升，做出来**高速抵抗**的话，也可以选择别的智壳优化阵容搭配了。）**水生绫：**阵容搭配同凌罗。（大招拥有**全体40%行动进度拉条**，更重要的是**减少**所有异格者和智壳**冷却1回合**。。。全队技能轮转快的飞起）被动技能还可以净化全体一个减益效果，**属于锦上添花**\n\n先写这些，后续会继续更新补充和完善。\n\n祝大家都可以在新赛季取得好成绩！尽情利用脑细胞，享受RTA酣战的感觉~~~\n\n大佬们有更多的想法和思路的话 ，评论区欢迎大家讨论和指正哈 ^_^For韶华",
  "assets": [
    "https://cdnimg-v2.gamekee.com/wiki2.0/avatar/1/21.png",
    "https://cdnimg-v2.gamekee.com/wiki2.0/images/w_1280/h_720/50364/154257/2026/2/10/935696.jpg",
    "https://cdnimg-v2.gamekee.com/wiki2.0/images/w_1920/h_1080/50364/664163/2025/7/25/51494.png",
    "https://cdnimg-v2.gamekee.com/wiki2.0/images/w_2000/h_2000/50364/664163/2025/2/31/787007.jpg",
    "https://cdnimg-v2.gamekee.com/wiki2.0/images/w_5000/h_2822/50364/664163/2025/8/4/657450.jpg",
    "https://cdnimg-v2.gamekee.com/wiki2.0/images/w_524/h_313/50364/789037/2025/8/27/896527.png",
    "https://cdnimg-v2.gamekee.com/wiki2.0/images/w_676/h_676/215/236746/2025/11/15/332900.png",
    "https://cdnimg-v2.gamekee.com/wiki2.0/images/w_676/h_676/215/236746/2025/11/15/36968.png",
    "https://cdnimg-v2.gamekee.com/wiki2.0/images/w_676/h_676/215/236746/2025/11/15/652839.png",
    "https://cdnimg-v2.gamekee.com/wiki2.0/images/w_676/h_676/215/236746/2025/11/15/862842.png",
    "https://cdnimg-v2.gamekee.com/wiki2.0/images/w_786/h_864/50364/789037/2025/10/18/413094.png",
    "https://cdnimg-v2.gamekee.com/wiki2.0/images/w_788/h_1056/50364/789037/2025/10/18/139407.png",
    "https://cdnimg-v2.gamekee.com/wiki2.0/images/w_789/h_870/50364/789037/2025/10/18/801153.png",
    "https://cdnimg-v2.gamekee.com/wiki2.0/images/w_888/h_207/50364/789037/2025/8/27/298274.png",
    "https://cdnimg-v2.gamekee.com/wiki2.0/images/w_900/h_500/50364/664163/2025/7/26/339253.jpg",
    "https://cdnimg-v2.gamekee.com/wiki2.0/images/w_960/h_540/50364/664163/2025/7/26/535320.jpg"
  ],
  "source": {
    "pageId": 678431,
    "title": "伊瑟PVP之RTA阵容推荐和搭配",
    "url": "https://www.gamekee.com/yise/678431.html",
    "updatedAt": "2025-11-18T08:20:31.000Z",
    "sourceFiles": {
      "markdown": "07_攻略评测/678431_伊瑟PVP之RTA阵容推荐和搭配.md",
      "metadata": "07_攻略评测/678431_伊瑟PVP之RTA阵容推荐和搭配.json",
      "rawApi": "_raw_api/details/678431.json"
    }
  }
}