{
  "id": 639256,
  "kind": "reference",
  "title": "都市异能策略回合制RPG《伊瑟》「原质测试」开启释出制作团队专访分享设计理念",
  "domainPath": [
    "04_公告活动资料",
    "01_公告资讯"
  ],
  "classifyReason": "公告或活动资料",
  "originalCategory": "01_公告资讯",
  "text": "都市异能策略回合制RPG《伊瑟》「原质测试」开启释出制作团队专访分享设计理念\n\n都市异能策略回合制RPG《伊瑟》官方今（24）日宣布正式开启为期12天的「原质测试」，开放iOS（TestFlight）、Android（官方APK）及PC版本三个平台，抢先体验成为「超链者」探索全新世界，并同步释出制作人专访，分享游戏设计理念。原质测试正式开启原质测试｜正式启动链结原质测试期间，玩\n\n都市异能策略回合制RPG《伊瑟》官方今（24）日宣布正式开启为期12 天的「原质测试」，开放iOS （TestFlight）、Android （官方APK）及PC 版本三个平台，抢先体验成为「超链者」探索全新世界，并同步释出制作人专访，分享游戏设计理念。\n\n原质测试正式开启\n\n原质测试｜正式启动链结\n\n原质测试期间，玩家将化身「超链者」，招募专属于自己的超链者小队探索「伊瑟Etheria」，完成协会指定的任务，在过程中携手「异格者」共同进行战斗、体验多人副本、组建协会结交伙伴，以及透过RTA 巅峰竞技场挑战来自各地的高手。\n\n本次测试为期12 天，参与本次测试玩家，通关指定关卡后，在未来游戏正式上市时将可取得纪念头像框——「原质先锋」。官方在测试期间，释出众多游戏福利，每日登入即可获得「伊瑟币」、「海德拉晶钻」、「异格原型」等虚宝道具，达成指定条件还可领取「SSR 角色」 。\n\n- 测试时间：2024 年10 月24 日11:00 - 2024 年11 月4 日11:00\n- 测试类型：不付费删档测试\n- 支援版本：PC-Windows、Android - 官方APK 包、iOS-TestFlight\n- 开放语音：中文配音、日文配音\n- 参加方式：前往官网选择对应平台下载进入，限量名额额满关闭。\n- 注意事项：「原质测试」为限量封闭测试，测试期间玩家帐号所产生的游戏资料均会在测试结束后删除！所有体验内容均为目前开发中版本，不代表游戏上线的最终品质和表现。\n\n此外，《伊瑟》官方粉丝团正推出抽奖活动，欢迎「超链者」们一同参与。\n\n各种福利天天领\n\n制作团队专访\n\nA：大家好，我们是《伊瑟》的研发团队，我是游戏制作人周健（Jack）很荣幸透过本次机会，与各位「超链者」分享游戏理念及开发过程的心得。\n\n《伊瑟》制作人周健(Jack)\n\nQ：首先《伊瑟》游戏主要特色是什么？游戏内最特殊的玩法为何？\n\nA：《伊瑟》是一款主打半即时制的回合卡牌RPG，与市面上的卡牌养成玩法不同的是，《伊瑟》更加注重在于「类魔灵」的核心玩法，并将游戏的养成门槛及内容做了一系列最佳化设定。透过固定的角色技能，搭配上多种不同的配套装备以及辅助宠物，来达成迥然的战斗风格。\n\n在体验过程中，《伊瑟》拥有箱庭式的主线关卡，鲜明的角色设定及沉浸十足的剧情，你将可以操作主角进行地形的探索，使用躲藏、跃动等方式来通过关卡。同时我们也预计在包含手机、PC、甚至是掌机上进行发布，提供更多元的游戏体验。期盼能为玩家们献上崭新风貌的回合战斗RPG。\n\n箱庭式的主线关卡玩法\n\nQ：《伊瑟》游戏的研发理念，以及其世界背景等设定是？\n\nA：研发团队成员受到《魔灵召唤》、《阴阳师》、《第七史诗》等注重兼具PVE 内容以及竞技要素的策略回合制游戏影响，也期望能亲手打造属于这类玩法的游戏，尝试带给玩家们更有趣，好玩且充满刺激的全新游戏体验。\n\n《伊瑟》的故事背景描述在一个未来世界，人类遭遇强大的天灾，于是开始将意识灵子化移植入虚拟世界「伊瑟Etheria」当中，而部分人们，也因此拥有强大的超能力，这些灵子生命体被称为「异格者」，他们原与人类一同和平共处。因为一场未知的病毒扩散，部分异格者开始对人类的产生侵略性，你将扮演着一名能与异格者相处的「超链者」，在冒险的过程中，结识许多伙伴，共同守护这个未来的虚拟世界。\n\n虚拟世界「伊瑟Etheria」\n\nQ：本作支援「即时竞技」(RTA) 的PVP 内容，能针对伊瑟的竞技性简单说明吗？\n\nA：《伊瑟》注重玩家们之间的竞技游戏体验，在游戏中有着多种不同的竞技玩法，提供所有玩家们酣畅淋漓的斗智体验，其中包含了以真人即时配对的竞技舞台(RTA)，透过配对到与你实力接近的玩家，运用BAN＆PICK 策略来组织你的战斗优势，在回合模式中精心策划你的每一动作指令，来战胜对手。\n\n未来我们也会规画各种线上及实体的竞技赛事，让玩家们可以有更大的舞台展示自己的谋略，本次封测也将抢先开放CBT「超链先锋赛」，还请擅长PVP 玩家们给予我们更多回馈与支持。\n\n《伊瑟》竞技场\n\nQ：能否大致介绍一下PVE 的内容以及其对应玩法。\n\nA：我们考量到现代社会的忙碌以及玩家对于游戏上手门槛等时代变化，《伊瑟》的整体PVE 采取「多元且休闲」的方向去进行设定，你可以选择体验的主线剧情，在箱庭式的关卡中肆意探索，透过隐匿、躲避怪物等机制来推近剧情，借此深入故事主题，或是培养心仪的角色，查看他们的故事，解锁更多的台词。\n\n亦可以挑战自身前往对应副本，获取角色经验、源器、智壳来使队伍成长壮大，除此之外，与志同道合的伙伴组织协会，协力挑战协会BOSS 等GVE 内容，同时在主角的形象上，也可以随时透过『衣柜』来随时替换服装，尽情打造属于自己的伊瑟之旅。\n\n依照个人进度，选择适合自己的PVE 玩法\n\n在衣柜中能替换各式服装外观\n\nQ：在游戏角色养成的体验上，能否透露给玩家们部分诀窍。\n\nA：先前有提到关于在养成上，我们希望降低养成负担的核心理念，因此，我们加入了「三倍速自动战斗」、「自动重复挑战」的设定，能够让玩家设定好之后，于游戏的背景环境下自行进行关卡的挑战，借此降低「肝的负担」。\n\n而在角色养成上，我们也将角色养成等机制门槛难度降低，只需要透过经验值道具即可快速进行升级，不需要养成大量的「升星素材」。另外，游戏中储备了众多的游戏活动，透过积极参加活动来取得资源，养成角色的负担将会大幅度降低，期盼玩家都能多方面尝试养成心仪的队伍，体验到游戏最核心的内容。\n\n伊瑟强调降低玩家培养角色的负担\n\nQ：可以分享一下在主角团中的成员以及设定吗？\n\nA：在初期，玩家将以「超链者」的身分的展开冒险，与俏皮可靠的代理人「麦琪」，踏上冒险的旅程，麦琪将会协助玩家们，进一步说明这个世界运行机制。而在冒险过程中，你将与主角团们(格雷、多乐丝、炼、卡奇) 相遇，这些成员来自于「异格者协会」，他们不仅风格鲜明，更是强力的战斗伙伴，将会陪伴们玩家逐渐解开源病毒危害的谜题。\n\n主角团出发解决任务\n\n游戏中每位角色都拥有自己的故事以及设定，例如强大的炼，在其过往有着不为人知的故事，这些故事，玩家将可以在「异格者」档案中解开。也请各位玩家不妨在游戏中查看，关于伊瑟世界中这些鲜明的角色，是如何形塑出他们的个人形象及性格。\n\n异格者档案及故事\n\n异格者语音展示\n\nQ：游戏中有许多势力，请问您最喜欢角色/ 最喜欢的势力是？\n\nA：游戏中的各个势力皆有其独特的魅力与价值取向，实在很难说最喜欢哪一个。每个角色也都有其个性表达，令人印象深刻。不过，「超链者」与「异格者」的组合在面对各种危机时展现出的勇气与智慧令人敬佩，他们为了保护伊瑟世界而不断努力的精神也非常值得赞赏。\n\n阵营－十三区高校展示\n\nQ：请介绍一下《伊瑟》声优最大特点为何？\n\nA：在声优上的选择上，我们也费了一番苦心，希望能带给玩家们更加沉浸的JRPG 式体验，研发团队在前后洽谈试配超过200 位日本声优老师，最终在全角色日配上，我们邀请子安武人、石川由依、大西沙织、小仓唯等50 余位声优老师强化角色演绎，前后耗时半年以上的时间逐句逐字调整，希望在战斗及剧情的表现上，都能带给玩家们最顶级的视听盛宴，另外，本次原质测试将会开放日文语音，也欢迎玩家们随时回馈给我们最真实的想法。\n\nQ：研发过程中是否有令您印象最深刻的艰难挑战？可与我们分享吗？\n\nA：在研发过程中，面临了许多挑战。其中，如何在传统的回合卡牌RPG (类魔灵) 框架上做出创新，同时确保游戏的品质和体验，是一个非常艰难的挑战。这部分需要我们在策略深度、关卡体验、角色养成等方面进行不断地尝试和突破，同时还要考虑到全球玩家的需求和回馈。\n\n此外，技术上的难题也不少，比如如何实现移动端主机级的关卡体验、如何确保游戏的稳定性和流畅性等。但是，透过团队的努力和合作，我们克服了这些困难，也让我们更加坚定了打造一款高品质游戏的信心。\n\nQ：有没有想对台港澳玩家群说的话呢？\n\nA：嗨！台湾、香港、澳门的玩家们，大家好！我们是《伊瑟》研发团队，非常高兴能够为各位展示我们的作品《伊瑟》，游戏仍处于开发阶段，仍有部分内容正在调整当中，我们也期盼能够透过本次的『原质测试』，详细的了解各位玩家的真实回馈，也请不吝的告诉我们关于你对《伊瑟》的真实想法。\n\n相信在不远的将来，我们将与各位正式见面！最后，希望众人们都能在伊瑟世界中，展开一场刺激畅快的冒险。",
  "assets": [
    "https://cdnimg-v2.gamekee.com/wiki2.0/images/215/4408/2022/0/13/227654.jpg",
    "https://cdnimg-v2.gamekee.com/wiki2.0/images/w_1280/h_960/50364/2024/10/24/78d622c7-9fb1-44bb-9b38-6c7c2b7aceb6.jpg",
    "https://cdnimg-v2.gamekee.com/wiki2.0/images/w_1920/h_1080/50364/2024/10/24/151f257e-dbe9-468a-8394-93efefdf9fed.jpg",
    "https://cdnimg-v2.gamekee.com/wiki2.0/images/w_1920/h_1080/50364/2024/10/24/1f32de07-9ee7-4393-8b91-cb343e58427c.jpg",
    "https://cdnimg-v2.gamekee.com/wiki2.0/images/w_1920/h_1080/50364/2024/10/24/275611c1-f30c-4c24-9e01-2d7aba6512ed.jpg",
    "https://cdnimg-v2.gamekee.com/wiki2.0/images/w_1920/h_1080/50364/2024/10/24/288bc423-f2b1-4a55-8e13-fff010854923.jpg",
    "https://cdnimg-v2.gamekee.com/wiki2.0/images/w_1920/h_1080/50364/2024/10/24/694cd0a5-0463-449e-9c39-8d9d319e3e05.jpg",
    "https://cdnimg-v2.gamekee.com/wiki2.0/images/w_1920/h_1080/50364/2024/10/24/6b34127c-1bca-402b-8e02-4a0d7d3f13f6.jpg",
    "https://cdnimg-v2.gamekee.com/wiki2.0/images/w_1920/h_1080/50364/2024/10/24/9683a28c-c2b6-4b09-9469-7755ead8f38b.jpg",
    "https://cdnimg-v2.gamekee.com/wiki2.0/images/w_1920/h_1080/50364/2024/10/24/9683a28c-c2b6-4b09-9469-7755ead8f38b.jpg,//cdnimg-v2.gamekee.com/wiki2.0/images/w_1920/h_1080/50364/2024/10/24/d47a4854-d4df-463d-8c38-656f0a6ed53d.jpg,//cdnimg-v2.gamekee.com/wiki2.0/images/w_1280/h_960/50364/2024/10/24/78d622c7-9fb1-44bb-9b38-6c7c2b7aceb6.jpg",
    "https://cdnimg-v2.gamekee.com/wiki2.0/images/w_1920/h_1080/50364/2024/10/24/9acac351-bd50-4418-900e-8a84eff5ada0.jpg",
    "https://cdnimg-v2.gamekee.com/wiki2.0/images/w_1920/h_1080/50364/2024/10/24/c269f30c-7e47-4195-8091-973ea2209632.jpg",
    "https://cdnimg-v2.gamekee.com/wiki2.0/images/w_1920/h_1080/50364/2024/10/24/d3a05c85-a5e2-42e0-ba0d-c933593cd8e4.jpg",
    "https://cdnimg-v2.gamekee.com/wiki2.0/images/w_1920/h_1080/50364/2024/10/24/d47a4854-d4df-463d-8c38-656f0a6ed53d.jpg",
    "https://cdnimg-v2.gamekee.com/wiki2.0/images/w_1920/h_1080/50364/2024/10/24/e4721714-c668-4a8b-b44a-7070dc2db272.jpg",
    "https://cdnimg-v2.gamekee.com/wiki2.0/images/w_2000/h_2000/50364/664163/2025/2/31/787007.jpg",
    "https://cdnimg-v2.gamekee.com/wiki2.0/images/w_676/h_676/215/236746/2025/11/15/332900.png",
    "https://cdnimg-v2.gamekee.com/wiki2.0/images/w_676/h_676/215/236746/2025/11/15/36968.png",
    "https://cdnimg-v2.gamekee.com/wiki2.0/images/w_676/h_676/215/236746/2025/11/15/652839.png",
    "https://cdnimg-v2.gamekee.com/wiki2.0/images/w_676/h_676/215/236746/2025/11/15/862842.png"
  ],
  "source": {
    "pageId": 639256,
    "title": "都市异能策略回合制RPG《伊瑟》「原质测试」开启释出制作团队专访分享设计理念",
    "url": "https://www.gamekee.com/yise/639256.html",
    "updatedAt": "2024-10-24T07:23:36.000Z",
    "sourceFiles": {
      "markdown": "01_公告资讯/639256_都市异能策略回合制RPG《伊瑟》「原质测试」开启释出制作团队专访分享设计理念.md",
      "metadata": "01_公告资讯/639256_都市异能策略回合制RPG《伊瑟》「原质测试」开启释出制作团队专访分享设计理念.json",
      "rawApi": "_raw_api/details/639256.json"
    }
  }
}