{
  "id": 620278,
  "kind": "character",
  "name": "安德鲁_坚盾",
  "entryName": "安德鲁_坚盾",
  "rarity": "R",
  "element": "异",
  "faction": "伊瑟E.O.S",
  "title": "坚盾",
  "gender": "男",
  "profession": "未公开",
  "identityCode": "E01-052132",
  "chipStatus": "正常",
  "assessment": "异格者安德鲁，身份编码E01-052132，Re-A芯片状态稳定，未见异常波动。\n安德鲁是伊吉斯安全公司的安全顾问兼雇员教官，曾服役于E.O.S.特别行动队，看上去是一名典型到不能再典型的雇佣保镖。作为前特勤部队成员，安德鲁熟练掌握各种常见的武器，会根据雇主的需求采取不同的安保策略。但现在，他响应了协会的征召，协助超链者执行各种任务。\n只不过由于习惯，安德鲁至今仍穿看那身饱经风霜的战术护甲，并且从不摘下头盔一一恐怕根本没人知道他究竟长么样，每当提起他的时候，大家不约而同想到的都是那副护甲面具。",
  "stats": {
    "生命": "9172+3167",
    "攻击": "542+279",
    "防御": "882+371",
    "速度": "112+9",
    "暴击率": "10%",
    "暴击伤害": "150%",
    "效果命中": "0%+32%",
    "效果抵抗": "0%+12%"
  },
  "skills": [
    {
      "skillId": "620278-skill-1",
      "order": 1,
      "section": "普攻",
      "name": "盾击 等级5",
      "icon": "https://cdnimg-v2.gamekee.com/wiki2.0/images/orc/role_picture4/83a8c8a9-e8d8-49ca-bde5-4f7965fc7afd.png",
      "description": "冷却时间：0\n安德鲁用巨盾攻击敌方；对敌方单体造成200%，额外附加自身防御60%的伤害。",
      "upgradeText": "等级2\n潜能提升：攻击力+25/攻击力+40/攻击力+5%/攻击力+60/攻击力+5%\n技能提升：伤害系数增加至180%\n等级3\n潜能提升：攻击力+100\n技能提升：自身防御附加伤害比例增加至50%\n等级4：\n潜能提升：速度值+3\n技能提升：伤害系数增加至200%\n等级5：\n潜能提升：速度值+6\n技能提升：自身防御附加伤害比例增加至60%",
      "tables": [
        {
          "title": "技能升级所需材料",
          "headers": [
            "潜能1",
            "潜能2",
            "潜能3",
            "潜能4",
            "等级2",
            "潜能5",
            "等级3",
            "潜能6",
            "等级4",
            "潜能7",
            "等级5"
          ],
          "rows": [
            [
              "(15)",
              "(15)",
              "(20)",
              "(20)",
              "(15)",
              "(20)",
              "(15)",
              "(20)",
              "(15)",
              "(15)",
              "(15)"
            ]
          ]
        }
      ]
    },
    {
      "skillId": "620278-skill-2",
      "order": 2,
      "section": "被动",
      "name": "坚韧意志 等级5",
      "icon": "https://cdnimg-v2.gamekee.com/wiki2.0/images/orc/role_picture5/21dce877-f3da-45f0-8f62-33266233bc14.png",
      "description": "冷却时间：0\n安德鲁生命降低至65%以下时，防御提升100%。",
      "upgradeText": "等级2\n潜能提升：防御力+15/防御力+25/防御力+5%/防御力+40/防御力+5%\n技能提升：防御提升效果增加至80%\n等级3\n潜能提升：防御力+70\n技能提升：防御提升效果增加至90%\n等级4：\n潜能提升：防御力+5%\n技能提升：防御提升效果增加至100%\n等级5：\n潜能提升：防御力+10%\n技能提升：触发防御提升的生命临界点上升到65%",
      "tables": [
        {
          "title": "技能升级所需材料",
          "headers": [
            "潜能1",
            "潜能2",
            "潜能3",
            "潜能4",
            "等级2",
            "潜能5",
            "等级3",
            "潜能6",
            "等级4",
            "潜能7",
            "等级5"
          ],
          "rows": [
            [
              "(15)",
              "(15)",
              "(20)",
              "(20)",
              "(15)",
              "(20)",
              "(15)",
              "(20)",
              "(15)",
              "(15)",
              "(15)"
            ]
          ]
        }
      ]
    },
    {
      "skillId": "620278-skill-3",
      "order": 3,
      "section": "必杀/终结技",
      "name": "防御姿态 等级5",
      "icon": "https://cdnimg-v2.gamekee.com/wiki2.0/images/orc/role_picture6/e358979f-76af-4d22-951c-bbb4062854c9.png",
      "description": "冷却时间：3\n安德鲁摆出防御姿态，强化盾牌；对全体敌人造成180%，额外附加自身防御60%的伤害，并有50%概率为目标附加2回合【防御下降】。",
      "upgradeText": "等级2\n潜能提升：生命值+250/生命值+400/生命值+5%/生命值+600/生命值+5%\n技能提升：自身防御附加伤害比例增加至50%\n等级3\n潜能提升：生命值+1000\n技能提升：【防御下降】持续回合增加至2回合\n等级4：\n潜能提升：效果命中+8%\n技能提升：自身防御附加伤害比例增加至60%\n等级5：\n潜能提升：效果命中+12%\n技能提升：技能冷却减少1回合",
      "tables": [
        {
          "title": "技能升级所需材料",
          "headers": [
            "潜能1",
            "潜能2",
            "潜能3",
            "潜能4",
            "等级2",
            "潜能5",
            "等级3",
            "潜能6",
            "等级4",
            "潜能7",
            "等级5"
          ],
          "rows": [
            [
              "(15)",
              "(15)",
              "(20)",
              "(20)",
              "(15)",
              "(20)",
              "(15)",
              "(20)",
              "(15)",
              "(15)",
              "(15)"
            ]
          ]
        }
      ]
    }
  ],
  "recommendations": [
    {
      "title": "推荐搭配",
      "name": "推荐",
      "descTitle": "角色简评",
      "description": "【战术定位】\n坦克\n【养成建议】\n┌─────────┬────────────┐\n| 技能优先级 | 555|\n| 源器配置 | 右三主属性3防御加成 |\n└─────────┴────────────┘\n【对局表现】\n防御输出型坦克，在坦度足够的情况下也能有一些额外输出，同时还可以削减对手防御为队伍创造输出空间",
      "attributes": [
        {
          "key": "推荐源器",
          "value": "12浴血+8荆棘+6巨壁屏障"
        },
        {
          "key": "推荐智壳",
          "value": "匠"
        },
        {
          "key": "推荐攻略",
          "value": "待补充..."
        }
      ],
      "attributesObject": {
        "推荐源器": "12浴血+8荆棘+6巨壁屏障",
        "推荐智壳": "匠",
        "推荐攻略": "待补充..."
      },
      "images": [
        "https://cdnimg-v2.gamekee.com/wiki2.0/images/w_300/h_242/50364/842288/2025/7/18/143293.png"
      ]
    }
  ],
  "upgrades": [
    {
      "section": "潜能",
      "title": "",
      "content": [
        "基础属性提升"
      ],
      "other": [
        "基础攻击力、防御力和生命值提升5%"
      ]
    },
    {
      "section": "潜能",
      "title": "",
      "content": [
        "效果命中提升"
      ],
      "other": [
        "效果命中+12%"
      ]
    },
    {
      "section": "潜能",
      "title": "",
      "content": [
        "基础属性提升"
      ],
      "other": [
        "基础攻击力、防御力和生命值提升5%"
      ]
    },
    {
      "section": "潜能",
      "title": "",
      "content": [
        "效果抵抗提升"
      ],
      "other": [
        "效果抵抗+12%"
      ]
    },
    {
      "section": "潜能",
      "title": "",
      "content": [
        "伤害提升和伤害减免"
      ],
      "other": [
        "造成伤害额外提升10%，受到伤害额外降低10%"
      ]
    }
  ],
  "archiveStories": [
    {
      "section": "异格档案",
      "tab": "记忆片段Ⅰ",
      "name": "记忆片段|",
      "icon": "",
      "description": "【伊吉斯安全公司应该给安德鲁发全勤奖。】\n伊吉斯安全公司专注于为艾尔特利斯的客户提供异格者安保雇佣服务，是一家颇具规模的私人安保企业。\n安德鲁属于公司里最勤奋的那类人。公司全勤纪录保持者、连续三年任务完成数排名第一、年度加班冠军的有力竟争者···即使前一天在安保任务中负伤，他也会在第二天继续出现在训练室里。这些勤奋刻苦的行为让安德鲁成为不少同事茶余饭后的谈资。\n当然了，每当这个时候，最激动的还得是训练室清洁工。每次工作间隙，他都会反戴帽子，声泪俱下地控诉安德鲁如何让他被迫加班。\n而罪魁祸首，这种时候一般都会蹲在一条小河边，静静地钓鱼。想必这是为数不多的，能让安德鲁放松的方式——至于能不能钓到鱼，或者钓上来的是鱼还是别的什么，这就全凭运气了。",
      "more": ""
    },
    {
      "section": "异格档案",
      "tab": "记忆片段Ⅱ",
      "name": "",
      "icon": "",
      "description": "【总有一天你会知道，队伍里有一个会做饭的人是多么幸运的事。】\n安德鲁的钓鱼技术可能一般，但他做鱼的技术绝对是一流的。\n据说某天深夜，伊吉斯安全公司接到了一项重要任务，全公司上上下下都因此加班到深夜。当忙碌了一天的员工们返回公司时，附近的饭馆早就都打烊了。疲惫大家已经没力气再做法了，只好计划着等到天亮再去找点东西吃。\n然而，当大家都准备空着肚子入睡的时候，走廊上竟然飘起了诱人的食物香味。肚子饿得咕咕叫的众人顺着香味找过去，发现香味源自员工宿舍的公共厨房，而厨房里站着一副拿着锅、系着围裙的战术护甲。\n呃，准确的说，是拿着锅、穿着战术护甲，并在护甲外面又套了围裙的安德鲁。\n安德鲁手中的锅里正是香味的源头一一一锅咸淡正好、色香味俱全的炖鱼。望着炖鱼，大家的眼泪不争气地从嘴角流了下来，而安德鲁也没有吝惜，又迅速地烧好了一桌子菜，和同事们分享。\n「我愿意为了这顿饭原谅他强迫我加班的事！」—一五星美食家兼伊吉斯安全公司训练室清洁工如是说。",
      "more": ""
    },
    {
      "section": "异格档案",
      "tab": "记忆片段Ⅲ",
      "name": "",
      "icon": "",
      "description": "【当然了，那副战术护甲偶尔也有带来麻烦的时候………】\n就算是那个铁人一样的安德鲁，偶尔也会有情绪低落的时候。\n据伊吉斯安全公司的后勤负责人说，安德鲁有一天突然找到她，询问有没有适合他的服装尺码的新式护甲。\n后勤负责人惊讶极了，毕竟在她看来，安德鲁的战术护甲就仿佛他的第二层皮肤，从不离身。后勤负责人实在想不出，究竟是由于什么原因，才会让安德鲁萌生出换新护甲的念头。\n在后勤负责人的再三追问下，安德鲁终于吞吞吐吐地说出了原因——原来那天早些时候，安德鲁跟着超链者前去执行清理源病毒的任务，但任务地点有不少感染者是熔断警察。在和感染者的战斗中，由于安德鲁的战术护甲和一些感染者的装备十分想死，有好几次其他异格者都错将他当成了敌人，这才让他动了换一身新护甲、减少这种情况发生的想法。\n后勤负责人当然全力支持安德鲁的想法，她找出了好几身全新的战术护甲让安德鲁一一尝试。然而，安德鲁早就习惯了旧式护甲的各种细节，在换上那些新护甲后，很难快速适应，甚至因为更换护甲导致的重心改变，在训练中好几次险些摔倒甚至出现危险情况。\n迫不得已，安德鲁只好情绪低落地换回了那身旧护甲。不过，后勤负责人相信，再过不久，合作带来的默契就能很快消除这种误会……大概吧？",
      "more": ""
    }
  ],
  "galleries": [
    {
      "title": "",
      "tabs": [
        {
          "title": "立绘-1",
          "type": "image",
          "images": [
            "https://cdnimg-v2.gamekee.com/wiki2.0/images/orc/role_picture1/297150e8-c408-423b-8332-30be1804ac37.png"
          ],
          "text": "//cdnimg-v2.gamekee.com/wiki2.0/images/orc/role_picture1/297150e8-c408-423b-8332-30be1804ac37.png"
        },
        {
          "title": "立绘-2",
          "type": "image",
          "images": [
            "https://cdnimg-v2.gamekee.com/wiki2.0/images/orc/role_picture2/c4c4c359-0962-4512-9936-5b392fee9c07.png"
          ],
          "text": "//cdnimg-v2.gamekee.com/wiki2.0/images/orc/role_picture2/c4c4c359-0962-4512-9936-5b392fee9c07.png"
        }
      ]
    }
  ],
  "images": [
    "https://cdnimg-v2.gamekee.com/wiki2.0/avatar/1/17.png",
    "https://cdnimg-v2.gamekee.com/wiki2.0/avatar/avatar_9.png",
    "https://cdnimg-v2.gamekee.com/wiki2.0/images/orc/role_picture1/297150e8-c408-423b-8332-30be1804ac37.png",
    "https://cdnimg-v2.gamekee.com/wiki2.0/images/orc/role_picture1/297150e8-c408-423b-8332-30be1804ac37.png,//cdnimg-v2.gamekee.com/wiki2.0/images/orc/role_picture2/c4c4c359-0962-4512-9936-5b392fee9c07.png,//cdnimg-v2.gamekee.com/wiki2.0/images/orc/role_picture3/e4c6898e-79c0-4477-864e-7030603b3af1.png",
    "https://cdnimg-v2.gamekee.com/wiki2.0/images/orc/role_picture2/c4c4c359-0962-4512-9936-5b392fee9c07.png",
    "https://cdnimg-v2.gamekee.com/wiki2.0/images/orc/role_picture3/e4c6898e-79c0-4477-864e-7030603b3af1.png",
    "https://cdnimg-v2.gamekee.com/wiki2.0/images/orc/role_picture4/83a8c8a9-e8d8-49ca-bde5-4f7965fc7afd.png",
    "https://cdnimg-v2.gamekee.com/wiki2.0/images/orc/role_picture5/21dce877-f3da-45f0-8f62-33266233bc14.png",
    "https://cdnimg-v2.gamekee.com/wiki2.0/images/orc/role_picture6/e358979f-76af-4d22-951c-bbb4062854c9.png",
    "https://cdnimg-v2.gamekee.com/wiki2.0/images/w_105/h_102/50364/157597/2024/3/16/666032.png",
    "https://cdnimg-v2.gamekee.com/wiki2.0/images/w_2000/h_2000/50364/664163/2025/2/31/787007.jpg",
    "https://cdnimg-v2.gamekee.com/wiki2.0/images/w_300/h_242/50364/842288/2025/7/18/143293.png",
    "https://cdnimg-v2.gamekee.com/wiki2.0/images/w_307/h_467/50364/355468/2025/4/13/464826.jpg",
    "https://cdnimg-v2.gamekee.com/wiki2.0/images/w_307/h_467/50364/664163/2024/11/25/336266.png",
    "https://cdnimg-v2.gamekee.com/wiki2.0/images/w_307/h_467/50364/664163/2024/11/25/447721.png",
    "https://cdnimg-v2.gamekee.com/wiki2.0/images/w_307/h_467/50364/664163/2024/11/25/61816.png",
    "https://cdnimg-v2.gamekee.com/wiki2.0/images/w_307/h_467/50364/664163/2024/11/25/775506.png",
    "https://cdnimg-v2.gamekee.com/wiki2.0/images/w_307/h_467/50364/664163/2024/11/25/85545.png",
    "https://cdnimg-v2.gamekee.com/wiki2.0/images/w_429/h_423/829/157597/2023/7/22/45380.png",
    "https://cdnimg-v2.gamekee.com/wiki2.0/images/w_56/h_56/50364/157597/2024/3/26/117794.png",
    "https://cdnimg-v2.gamekee.com/wiki2.0/images/w_65/h_65/50364/355468/2025/4/12/357114.png",
    "https://cdnimg-v2.gamekee.com/wiki2.0/images/w_65/h_65/50364/355468/2025/4/12/364402.png",
    "https://cdnimg-v2.gamekee.com/wiki2.0/images/w_65/h_65/50364/355468/2025/4/12/382722.png",
    "https://cdnimg-v2.gamekee.com/wiki2.0/images/w_65/h_65/50364/355468/2025/4/12/530081.png",
    "https://cdnimg-v2.gamekee.com/wiki2.0/images/w_65/h_65/50364/355468/2025/4/12/758801.png",
    "https://cdnimg-v2.gamekee.com/wiki2.0/images/w_676/h_676/215/236746/2025/11/15/332900.png",
    "https://cdnimg-v2.gamekee.com/wiki2.0/images/w_676/h_676/215/236746/2025/11/15/36968.png",
    "https://cdnimg-v2.gamekee.com/wiki2.0/images/w_676/h_676/215/236746/2025/11/15/652839.png",
    "https://cdnimg-v2.gamekee.com/wiki2.0/images/w_676/h_676/215/236746/2025/11/15/862842.png"
  ],
  "source": {
    "pageId": 620278,
    "title": "安德鲁_坚盾",
    "url": "https://www.gamekee.com/yise/620278.html",
    "updatedAt": "2025-08-18T07:38:36.000Z",
    "sourceFiles": {
      "markdown": "03_图鉴词条/620278_安德鲁_坚盾.md",
      "metadata": "03_图鉴词条/620278_安德鲁_坚盾.json",
      "rawApi": "_raw_api/details/620278.json"
    }
  }
}