{
  "id": 679814,
  "kind": "cleanup_candidate",
  "title": "什么时候开S6新区啊，是每周四开新区吗，上一次还是10月9号.",
  "domainPath": [
    "99_待清洗",
    "03_未归类资料"
  ],
  "classifyReason": "暂无足够规则判定到正式知识区",
  "originalCategory": "09_社区帖子",
  "text": "什么时候开S6新区啊，是每周四开新区吗，上一次还是10月9号.\n\n什么时候开S6新区啊，是每周四开新区吗，上一次还是10月9号.\n\n什么时候开S6新区啊，是每周四开新区吗，上一次还是10月9号.",
  "assets": [
    "https://cdnimg-v2.gamekee.com/wiki2.0/images/w_2000/h_2000/50364/664163/2025/2/31/787007.jpg",
    "https://cdnimg-v2.gamekee.com/wiki2.0/images/w_676/h_676/215/236746/2025/11/15/332900.png",
    "https://cdnimg-v2.gamekee.com/wiki2.0/images/w_676/h_676/215/236746/2025/11/15/36968.png",
    "https://cdnimg-v2.gamekee.com/wiki2.0/images/w_676/h_676/215/236746/2025/11/15/652839.png",
    "https://cdnimg-v2.gamekee.com/wiki2.0/images/w_676/h_676/215/236746/2025/11/15/862842.png"
  ],
  "source": {
    "pageId": 679814,
    "title": "什么时候开S6新区啊，是每周四开新区吗，上一次还是10月9号.",
    "url": "https://www.gamekee.com/yise/679814.html",
    "updatedAt": "2025-10-15T06:05:21.000Z",
    "sourceFiles": {
      "markdown": "09_社区帖子/679814_什么时候开S6新区啊，是每周四开新区吗，上一次还是10月9号..md",
      "metadata": "09_社区帖子/679814_什么时候开S6新区啊，是每周四开新区吗，上一次还是10月9号..json",
      "rawApi": "_raw_api/details/679814.json"
    }
  }
}